<annotation>
	<folder>img4</folder>
	<filename>g40069.jpg</filename>
	<path>E:\dianwang_detection_train\img4\g40069.jpg</path>
	<source>
		<database>Unknown</database>
	</source>
	<size>
		<width>4344</width>
		<height>5792</height>
		<depth>3</depth>
	</size>
	<segmented>0</segmented>
	<object>
		<name>downsuit</name>
		<pose>Unspecified</pose>
		<truncated>0</truncated>
		<difficult>0</difficult>
		<bndbox>
			<xmin>1646</xmin>
			<ymin>2651</ymin>
			<xmax>2427</xmax>
			<ymax>4294</ymax>
		</bndbox>
	</object>
	<object>
		<name>person</name>
		<pose>Unspecified</pose>
		<truncated>0</truncated>
		<difficult>0</difficult>
		<bndbox>
			<xmin>3964</xmin>
			<ymin>3536</ymin>
			<xmax>4320</xmax>
			<ymax>4452</ymax>
		</bndbox>
	</object>
	<object>
		<name>person</name>
		<pose>Unspecified</pose>
		<truncated>0</truncated>
		<difficult>0</difficult>
		<bndbox>
			<xmin>1433</xmin>
			<ymin>1008</ymin>
			<xmax>2532</xmax>
			<ymax>4581</ymax>
		</bndbox>
	</object>
	<object>
		<name>downcloth</name>
		<pose>Unspecified</pose>
		<truncated>0</truncated>
		<difficult>0</difficult>
		<bndbox>
			<xmin>4019</xmin>
			<ymin>4044</ymin>
			<xmax>4270</xmax>
			<ymax>4395</ymax>
		</bndbox>
	</object>
	<object>
		<name>upsuit</name>
		<pose>Unspecified</pose>
		<truncated>0</truncated>
		<difficult>0</difficult>
		<bndbox>
			<xmin>1639</xmin>
			<ymin>1274</ymin>
			<xmax>2530</xmax>
			<ymax>2601</ymax>
		</bndbox>
	</object>
	<object>
		<name>upcloth</name>
		<pose>Unspecified</pose>
		<truncated>0</truncated>
		<difficult>0</difficult>
		<bndbox>
			<xmin>3993</xmin>
			<ymin>3671</ymin>
			<xmax>4305</xmax>
			<ymax>4026</ymax>
		</bndbox>
	</object>
	<object>
		<name>unhalt</name>
		<pose>Unspecified</pose>
		<truncated>0</truncated>
		<difficult>0</difficult>
		<bndbox>
			<xmin>4030</xmin>
			<ymin>3545</ymin>
			<xmax>4156</xmax>
			<ymax>3685</ymax>
		</bndbox>
	</object>
	<object>
		<name>person</name>
		<pose>Unspecified</pose>
		<truncated>0</truncated>
		<difficult>0</difficult>
		<bndbox>
			<xmin>3143</xmin>
			<ymin>3518</ymin>
			<xmax>3489</xmax>
			<ymax>4364</ymax>
		</bndbox>
	</object>
	<object>
		<name>unhalt</name>
		<pose>Unspecified</pose>
		<truncated>0</truncated>
		<difficult>0</difficult>
		<bndbox>
			<xmin>3245</xmin>
			<ymin>3521</ymin>
			<xmax>3360</xmax>
			<ymax>3663</ymax>
		</bndbox>
	</object>
	<object>
		<name>downcloth</name>
		<pose>Unspecified</pose>
		<truncated>0</truncated>
		<difficult>0</difficult>
		<bndbox>
			<xmin>3237</xmin>
			<ymin>3965</ymin>
			<xmax>3444</xmax>
			<ymax>4277</ymax>
		</bndbox>
	</object>
	<object>
		<name>upcloth</name>
		<pose>Unspecified</pose>
		<truncated>0</truncated>
		<difficult>0</difficult>
		<bndbox>
			<xmin>3176</xmin>
			<ymin>3654</ymin>
			<xmax>3425</xmax>
			<ymax>3960</ymax>
		</bndbox>
	</object>
	<object>
		<name>hand</name>
		<pose>Unspecified</pose>
		<truncated>0</truncated>
		<difficult>0</difficult>
		<bndbox>
			<xmin>1480</xmin>
			<ymin>991</ymin>
			<xmax>1771</xmax>
			<ymax>1273</ymax>
		</bndbox>
	</object>
	<object>
		<name>safebelt</name>
		<pose>Unspecified</pose>
		<truncated>0</truncated>
		<difficult>0</difficult>
		<bndbox>
			<xmin>939</xmin>
			<ymin>1014</ymin>
			<xmax>2580</xmax>
			<ymax>3187</ymax>
		</bndbox>
	</object>
</annotation>
