<annotation>
	<folder>img</folder>
	<filename>image_auZpPK.jpg</filename>
	<path>G:\nfdw_datasets_0313\img\image_auZpPK.jpg</path>
	<source>
		<database>Unknown</database>
	</source>
	<size>
		<width>1440</width>
		<height>1080</height>
		<depth>3</depth>
	</size>
	<segmented>0</segmented>
	<object>
		<name>unhalt</name>
		<pose>Unspecified</pose>
		<truncated>0</truncated>
		<difficult>0</difficult>
		<bndbox>
			<xmin>459</xmin>
			<ymin>274</ymin>
			<xmax>551</xmax>
			<ymax>377</ymax>
		</bndbox>
	</object>
	<object>
		<name>halt</name>
		<pose>Unspecified</pose>
		<truncated>0</truncated>
		<difficult>0</difficult>
		<bndbox>
			<xmin>933</xmin>
			<ymin>333</ymin>
			<xmax>1022</xmax>
			<ymax>437</ymax>
		</bndbox>
	</object>
	<object>
		<name>upsuit</name>
		<pose>Unspecified</pose>
		<truncated>0</truncated>
		<difficult>0</difficult>
		<bndbox>
			<xmin>416</xmin>
			<ymin>360</ymin>
			<xmax>564</xmax>
			<ymax>598</ymax>
		</bndbox>
	</object>
	<object>
		<name>person</name>
		<pose>Unspecified</pose>
		<truncated>0</truncated>
		<difficult>0</difficult>
		<bndbox>
			<xmin>848</xmin>
			<ymin>330</ymin>
			<xmax>1028</xmax>
			<ymax>873</ymax>
		</bndbox>
	</object>
	<object>
		<name>person</name>
		<pose>Unspecified</pose>
		<truncated>0</truncated>
		<difficult>0</difficult>
		<bndbox>
			<xmin>413</xmin>
			<ymin>273</ymin>
			<xmax>589</xmax>
			<ymax>911</ymax>
		</bndbox>
	</object>
	<object>
		<name>downsuit</name>
		<pose>Unspecified</pose>
		<truncated>0</truncated>
		<difficult>0</difficult>
		<bndbox>
			<xmin>433</xmin>
			<ymin>614</ymin>
			<xmax>551</xmax>
			<ymax>883</ymax>
		</bndbox>
	</object>
	<object>
		<name>downsuit</name>
		<pose>Unspecified</pose>
		<truncated>0</truncated>
		<difficult>0</difficult>
		<bndbox>
			<xmin>867</xmin>
			<ymin>613</ymin>
			<xmax>977</xmax>
			<ymax>829</ymax>
		</bndbox>
	</object>
	<object>
		<name>upsuit</name>
		<pose>Unspecified</pose>
		<truncated>0</truncated>
		<difficult>0</difficult>
		<bndbox>
			<xmin>851</xmin>
			<ymin>410</ymin>
			<xmax>1005</xmax>
			<ymax>588</ymax>
		</bndbox>
	</object>
	<object>
		<name>hand</name>
		<pose>Unspecified</pose>
		<truncated>0</truncated>
		<difficult>0</difficult>
		<bndbox>
			<xmin>561</xmin>
			<ymin>468</ymin>
			<xmax>584</xmax>
			<ymax>514</ymax>
		</bndbox>
	</object>
	<object>
		<name>safebelt</name>
		<pose>Unspecified</pose>
		<truncated>0</truncated>
		<difficult>0</difficult>
		<bndbox>
			<xmin>879</xmin>
			<ymin>419</ymin>
			<xmax>1004</xmax>
			<ymax>706</ymax>
		</bndbox>
	</object>
	<object>
		<name>noear</name>
		<pose>Unspecified</pose>
		<truncated>0</truncated>
		<difficult>0</difficult>
		<bndbox>
			<xmin>480</xmin>
			<ymin>319</ymin>
			<xmax>516</xmax>
			<ymax>362</ymax>
		</bndbox>
	</object>
	<object>
		<name>inear</name>
		<pose>Unspecified</pose>
		<truncated>0</truncated>
		<difficult>0</difficult>
		<bndbox>
			<xmin>931</xmin>
			<ymin>386</ymin>
			<xmax>956</xmax>
			<ymax>430</ymax>
		</bndbox>
	</object>
	<object>
		<name>hand</name>
		<pose>Unspecified</pose>
		<truncated>0</truncated>
		<difficult>0</difficult>
		<bndbox>
			<xmin>936</xmin>
			<ymin>540</ymin>
			<xmax>976</xmax>
			<ymax>593</ymax>
		</bndbox>
	</object>
	<object>
		<name>hand</name>
		<pose>Unspecified</pose>
		<truncated>0</truncated>
		<difficult>0</difficult>
		<bndbox>
			<xmin>983</xmin>
			<ymin>542</ymin>
			<xmax>1010</xmax>
			<ymax>580</ymax>
		</bndbox>
	</object>
</annotation>
