<annotation>
	<folder>img6</folder>
	<filename>image_DIpVOk.jpg</filename>
	<path>G:\6\img6\image_DIpVOk.jpg</path>
	<source>
		<database>Unknown</database>
	</source>
	<size>
		<width>960</width>
		<height>720</height>
		<depth>3</depth>
	</size>
	<segmented>0</segmented>
	<object>
		<name>person</name>
		<pose>Unspecified</pose>
		<truncated>1</truncated>
		<difficult>0</difficult>
		<bndbox>
			<xmin>222</xmin>
			<ymin>151</ymin>
			<xmax>467</xmax>
			<ymax>720</ymax>
		</bndbox>
	</object>
	<object>
		<name>person</name>
		<pose>Unspecified</pose>
		<truncated>1</truncated>
		<difficult>0</difficult>
		<bndbox>
			<xmin>1</xmin>
			<ymin>87</ymin>
			<xmax>196</xmax>
			<ymax>720</ymax>
		</bndbox>
	</object>
	<object>
		<name>halt</name>
		<pose>Unspecified</pose>
		<truncated>0</truncated>
		<difficult>0</difficult>
		<bndbox>
			<xmin>292</xmin>
			<ymin>155</ymin>
			<xmax>390</xmax>
			<ymax>256</ymax>
		</bndbox>
	</object>
	<object>
		<name>downsuit</name>
		<pose>Unspecified</pose>
		<truncated>1</truncated>
		<difficult>0</difficult>
		<bndbox>
			<xmin>253</xmin>
			<ymin>503</ymin>
			<xmax>415</xmax>
			<ymax>720</ymax>
		</bndbox>
	</object>
	<object>
		<name>halt</name>
		<pose>Unspecified</pose>
		<truncated>1</truncated>
		<difficult>0</difficult>
		<bndbox>
			<xmin>1</xmin>
			<ymin>93</ymin>
			<xmax>119</xmax>
			<ymax>246</ymax>
		</bndbox>
	</object>
	<object>
		<name>upsuit</name>
		<pose>Unspecified</pose>
		<truncated>0</truncated>
		<difficult>0</difficult>
		<bndbox>
			<xmin>222</xmin>
			<ymin>252</ymin>
			<xmax>454</xmax>
			<ymax>493</ymax>
		</bndbox>
	</object>
	<object>
		<name>upsuit</name>
		<pose>Unspecified</pose>
		<truncated>1</truncated>
		<difficult>0</difficult>
		<bndbox>
			<xmin>1</xmin>
			<ymin>231</ymin>
			<xmax>192</xmax>
			<ymax>563</ymax>
		</bndbox>
	</object>
	<object>
		<name>badge</name>
		<pose>Unspecified</pose>
		<truncated>0</truncated>
		<difficult>0</difficult>
		<bndbox>
			<xmin>225</xmin>
			<ymin>341</ymin>
			<xmax>268</xmax>
			<ymax>406</ymax>
		</bndbox>
	</object>
	<object>
		<name>downsuit</name>
		<pose>Unspecified</pose>
		<truncated>1</truncated>
		<difficult>0</difficult>
		<bndbox>
			<xmin>1</xmin>
			<ymin>575</ymin>
			<xmax>156</xmax>
			<ymax>720</ymax>
		</bndbox>
	</object>
	<object>
		<name>longglove</name>
		<pose>Unspecified</pose>
		<truncated>0</truncated>
		<difficult>0</difficult>
		<bndbox>
			<xmin>227</xmin>
			<ymin>404</ymin>
			<xmax>276</xmax>
			<ymax>512</ymax>
		</bndbox>
	</object>
	<object>
		<name>testrod</name>
		<pose>Unspecified</pose>
		<truncated>0</truncated>
		<difficult>0</difficult>
		<bndbox>
			<xmin>460</xmin>
			<ymin>346</ymin>
			<xmax>534</xmax>
			<ymax>393</ymax>
		</bndbox>
	</object>
	<object>
		<name>inear</name>
		<pose>Unspecified</pose>
		<truncated>0</truncated>
		<difficult>0</difficult>
		<bndbox>
			<xmin>43</xmin>
			<ymin>168</ymin>
			<xmax>95</xmax>
			<ymax>226</ymax>
		</bndbox>
	</object>
	<object>
		<name>inear</name>
		<pose>Unspecified</pose>
		<truncated>0</truncated>
		<difficult>0</difficult>
		<bndbox>
			<xmin>348</xmin>
			<ymin>212</ymin>
			<xmax>376</xmax>
			<ymax>259</ymax>
		</bndbox>
	</object>
</annotation>
